museflow/__init__.py
museflow/flexible_server.py
museflow/museflow.py
museflow/museflow_dev_server.py
museflow/element/__init__.py
museflow/element/element.py
museflow/element/element_factory.py
museflow/element/inventory.py
museflow/element/inventory_fft.py
museflow/element/style.py
museflow/museflow_webpage/dev_server.py
museflow/museflow_webpage/component/countdown/countdown.py
museflow/museflow_webpage/component/countdown/countdown_script.py
museflow/museflow_webpage/component/dialer/dialer.py
museflow/museflow_webpage/component/dialer/dialer_script.py
museflow/museflow_webpage/component/home/home.py
museflow/museflow_webpage/component/home/image_to_base64.py
museflow/museflow_webpage/component/theme_slider/theme_slider.py
museflow/museflow_webpage/component/theme_slider/theme_slider_script.py
museflow/museflow_webpage/style/palette.py
museflow/museflow_webpage/style/style.py
museflow/pyjs_compiler/__init__.py
museflow/pyjs_compiler/pyjs_compiler.py
museflow/pyjs_compiler/pyjs_compiler_unit_abs.py
museflow/pyjs_compiler/pyjs_dispatcher.py
museflow/pyjs_compiler/pyjs_nexus.py
museflow/pyjs_compiler/pyjs_compiler_units/__init__.py
museflow/pyjs_compiler/pyjs_compiler_units/assign_unit.py
museflow/pyjs_compiler/pyjs_compiler_units/augassign_unit.py
museflow/pyjs_compiler/pyjs_compiler_units/binop_unit.py
museflow/pyjs_compiler/pyjs_compiler_units/bool_unit.py
museflow/pyjs_compiler/pyjs_compiler_units/boolop_unit.py
museflow/pyjs_compiler/pyjs_compiler_units/break_unit.py
museflow/pyjs_compiler/pyjs_compiler_units/call_unit.py
museflow/pyjs_compiler/pyjs_compiler_units/compare_unit.py
museflow/pyjs_compiler/pyjs_compiler_units/constant_unit.py
museflow/pyjs_compiler/pyjs_compiler_units/continue_unit.py
museflow/pyjs_compiler/pyjs_compiler_units/dict_unit.py
museflow/pyjs_compiler/pyjs_compiler_units/expr_unit.py
museflow/pyjs_compiler/pyjs_compiler_units/float_unit.py
museflow/pyjs_compiler/pyjs_compiler_units/fstring_unit.py
python_museflow-0.0.3.dist-info/METADATA
python_museflow-0.0.3.dist-info/WHEEL
python_museflow-0.0.3.dist-info/top_level.txt
python_museflow-0.0.3.dist-info/RECORD
