Metadata-Version: 2.4
Name: python-museflow
Version: 0.0.3
Summary: MuseFlow is a Python framework for developing full-stack applications entirely in Python, eliminating the need for HTML, CSS, or JavaScript
Author-email: Omer Menashe <unspecified@mail.com>
License: Proprietary, All Rights Reserved
Project-URL: Source, https://github.com/iamomerm/Museflow
Keywords: python-museflow,museflow
Classifier: Programming Language :: Python :: 3
Classifier: Operating System :: OS Independent
Requires-Python: >=3.7
Requires-Dist: certifi==2025.11.12
Requires-Dist: cffi==2.0.0
Requires-Dist: charset-normalizer==3.4.4
Requires-Dist: cryptography==46.0.3
Requires-Dist: greenlet==3.2.4
Requires-Dist: idna==3.11
Requires-Dist: lxml==6.0.2
Requires-Dist: playwright==1.56.0
Requires-Dist: pycparser==2.23
Requires-Dist: pyee==13.0.0
Requires-Dist: requests==2.32.5
Requires-Dist: smart_open==7.5.0
Requires-Dist: streaming-form-data==1.19.1
Requires-Dist: syntax-checker==0.4.0
Requires-Dist: typing_extensions==4.15.0
Requires-Dist: urllib3==2.5.0
Requires-Dist: wrapt==2.0.1
Requires-Dist: websockets==15.0.1
